[
  {
    "id": 1512,
    "tournament": {
      "id": 124,
      "name": "KQSFL Draft Night 2/27/23",
      "scene": 9,
      "scene_name": "sfl",
      "slug": "kqsfl-draft-night-22723",
      "date": "2023-02-27",
      "is_active": false,
      "location": "",
      "description": "",
      "allow_registration": false,
      "registration_close_date": null,
      "registration_banner": null,
      "accept_payments": false,
      "link_type": "challonge",
      "registration_message": "",
      "payment_message": "",
      "stripe_configured": false,
      "awards": null,
      "require_player_photo": false,
      "assigned_cabinets": [],
      "tidbit_prompt": "Interesting tidbit about yourself",
      "scene_display_name": "South Florida"
    },
    "stage_name": "KQSFL Draft Night 2/27/23",
    "blue_team_info": {
      "id": 732,
      "name": "PRECIOUS",
      "image": null
    },
    "gold_team_info": {
      "id": 729,
      "name": "SHIPWASH",
      "image": null
    },
    "bracket_info": {
      "id": 242,
      "name": "KQSFL Draft Night 2/27/23",
      "linked_bracket_id": "KQSFL_022723",
      "link_token": "6b8fa6203a8a85887c346ed8ef5f5115",
      "linked_org": null,
      "is_valid": true,
      "is_complete": false,
      "rounds_per_match": 0,
      "wins_per_match": 2,
      "matches_per_opponent": null,
      "report_as_sets": false,
      "add_tiebreaker": false,
      "stage_type": null,
      "auto_warmup": "false",
      "queue_timer": 30,
      "randomize_sides": false,
      "third_place_match": false,
      "stage_tiebreakers": null,
      "tournament": 124
    },
    "linked_match_id": "309613085",
    "match_type": null,
    "match_num": null,
    "blue_score": 0,
    "gold_score": 0,
    "round_num": null,
    "round_name": "Quarterfinals",
    "is_flipped": false,
    "is_complete": false,
    "is_warmup": false,
    "video_link": null,
    "winner_to_team": null,
    "loser_to_team": null,
    "winner_place": null,
    "loser_place": null,
    "bracket": 242,
    "blue_team": 732,
    "gold_team": 729,
    "active_cabinet": null,
    "winner_to_match": null,
    "loser_to_match": null
  },
  {
    "id": 1513,
    "tournament": {
      "id": 124,
      "name": "KQSFL Draft Night 2/27/23",
      "scene": 9,
      "scene_name": "sfl",
      "slug": "kqsfl-draft-night-22723",
      "date": "2023-02-27",
      "is_active": false,
      "location": "",
      "description": "",
      "allow_registration": false,
      "registration_close_date": null,
      "registration_banner": null,
      "accept_payments": false,
      "link_type": "challonge",
      "registration_message": "",
      "payment_message": "",
      "stripe_configured": false,
      "awards": null,
      "require_player_photo": false,
      "assigned_cabinets": [],
      "tidbit_prompt": "Interesting tidbit about yourself",
      "scene_display_name": "South Florida"
    },
    "stage_name": "KQSFL Draft Night 2/27/23",
    "blue_team_info": {
      "id": 734,
      "name": "GLAMARIS",
      "image": null
    },
    "gold_team_info": {
      "id": 735,
      "name": "HOWL",
      "image": null
    },
    "bracket_info": {
      "id": 242,
      "name": "KQSFL Draft Night 2/27/23",
      "linked_bracket_id": "KQSFL_022723",
      "link_token": "6b8fa6203a8a85887c346ed8ef5f5115",
      "linked_org": null,
      "is_valid": true,
      "is_complete": false,
      "rounds_per_match": 0,
      "wins_per_match": 2,
      "matches_per_opponent": null,
      "report_as_sets": false,
      "add_tiebreaker": false,
      "stage_type": null,
      "auto_warmup": "false",
      "queue_timer": 30,
      "randomize_sides": false,
      "third_place_match": false,
      "stage_tiebreakers": null,
      "tournament": 124
    },
    "linked_match_id": "309613086",
    "match_type": null,
    "match_num": null,
    "blue_score": 0,
    "gold_score": 0,
    "round_num": null,
    "round_name": "Quarterfinals",
    "is_flipped": false,
    "is_complete": false,
    "is_warmup": false,
    "video_link": null,
    "winner_to_team": null,
    "loser_to_team": null,
    "winner_place": null,
    "loser_place": null,
    "bracket": 242,
    "blue_team": 734,
    "gold_team": 735,
    "active_cabinet": null,
    "winner_to_match": null,
    "loser_to_match": null
  },
  {
    "id": 1514,
    "tournament": {
      "id": 124,
      "name": "KQSFL Draft Night 2/27/23",
      "scene": 9,
      "scene_name": "sfl",
      "slug": "kqsfl-draft-night-22723",
      "date": "2023-02-27",
      "is_active": false,
      "location": "",
      "description": "",
      "allow_registration": false,
      "registration_close_date": null,
      "registration_banner": null,
      "accept_payments": false,
      "link_type": "challonge",
      "registration_message": "",
      "payment_message": "",
      "stripe_configured": false,
      "awards": null,
      "require_player_photo": false,
      "assigned_cabinets": [],
      "tidbit_prompt": "Interesting tidbit about yourself",
      "scene_display_name": "South Florida"
    },
    "stage_name": "KQSFL Draft Night 2/27/23",
    "blue_team_info": {
      "id": 733,
      "name": "DAN",
      "image": null
    },
    "gold_team_info": {
      "id": 730,
      "name": "MASTERJOE",
      "image": null
    },
    "bracket_info": {
      "id": 242,
      "name": "KQSFL Draft Night 2/27/23",
      "linked_bracket_id": "KQSFL_022723",
      "link_token": "6b8fa6203a8a85887c346ed8ef5f5115",
      "linked_org": null,
      "is_valid": true,
      "is_complete": false,
      "rounds_per_match": 0,
      "wins_per_match": 2,
      "matches_per_opponent": null,
      "report_as_sets": false,
      "add_tiebreaker": false,
      "stage_type": null,
      "auto_warmup": "false",
      "queue_timer": 30,
      "randomize_sides": false,
      "third_place_match": false,
      "stage_tiebreakers": null,
      "tournament": 124
    },
    "linked_match_id": "309613087",
    "match_type": null,
    "match_num": null,
    "blue_score": 0,
    "gold_score": 0,
    "round_num": null,
    "round_name": "Quarterfinals",
    "is_flipped": false,
    "is_complete": false,
    "is_warmup": false,
    "video_link": null,
    "winner_to_team": null,
    "loser_to_team": null,
    "winner_place": null,
    "loser_place": null,
    "bracket": 242,
    "blue_team": 733,
    "gold_team": 730,
    "active_cabinet": null,
    "winner_to_match": null,
    "loser_to_match": null
  },
  {
    "id": 1515,
    "tournament": {
      "id": 124,
      "name": "KQSFL Draft Night 2/27/23",
      "scene": 9,
      "scene_name": "sfl",
      "slug": "kqsfl-draft-night-22723",
      "date": "2023-02-27",
      "is_active": false,
      "location": "",
      "description": "",
      "allow_registration": false,
      "registration_close_date": null,
      "registration_banner": null,
      "accept_payments": false,
      "link_type": "challonge",
      "registration_message": "",
      "payment_message": "",
      "stripe_configured": false,
      "awards": null,
      "require_player_photo": false,
      "assigned_cabinets": [],
      "tidbit_prompt": "Interesting tidbit about yourself",
      "scene_display_name": "South Florida"
    },
    "stage_name": "KQSFL Draft Night 2/27/23",
    "blue_team_info": {
      "id": 729,
      "name": "SHIPWASH",
      "image": null
    },
    "gold_team_info": {
      "id": 732,
      "name": "PRECIOUS",
      "image": null
    },
    "bracket_info": {
      "id": 242,
      "name": "KQSFL Draft Night 2/27/23",
      "linked_bracket_id": "KQSFL_022723",
      "link_token": "6b8fa6203a8a85887c346ed8ef5f5115",
      "linked_org": null,
      "is_valid": true,
      "is_complete": false,
      "rounds_per_match": 0,
      "wins_per_match": 2,
      "matches_per_opponent": null,
      "report_as_sets": false,
      "add_tiebreaker": false,
      "stage_type": null,
      "auto_warmup": "false",
      "queue_timer": 30,
      "randomize_sides": false,
      "third_place_match": false,
      "stage_tiebreakers": null,
      "tournament": 124
    },
    "linked_match_id": "309613299",
    "match_type": null,
    "match_num": null,
    "blue_score": 0,
    "gold_score": 2,
    "round_num": null,
    "round_name": "Round 1",
    "is_flipped": true,
    "is_complete": false,
    "is_warmup": false,
    "video_link": null,
    "winner_to_team": null,
    "loser_to_team": null,
    "winner_place": null,
    "loser_place": null,
    "bracket": 242,
    "blue_team": 729,
    "gold_team": 732,
    "active_cabinet": null,
    "winner_to_match": null,
    "loser_to_match": null
  },
  {
    "id": 1516,
    "tournament": {
      "id": 124,
      "name": "KQSFL Draft Night 2/27/23",
      "scene": 9,
      "scene_name": "sfl",
      "slug": "kqsfl-draft-night-22723",
      "date": "2023-02-27",
      "is_active": false,
      "location": "",
      "description": "",
      "allow_registration": false,
      "registration_close_date": null,
      "registration_banner": null,
      "accept_payments": false,
      "link_type": "challonge",
      "registration_message": "",
      "payment_message": "",
      "stripe_configured": false,
      "awards": null,
      "require_player_photo": false,
      "assigned_cabinets": [],
      "tidbit_prompt": "Interesting tidbit about yourself",
      "scene_display_name": "South Florida"
    },
    "stage_name": "KQSFL Draft Night 2/27/23",
    "blue_team_info": {
      "id": 735,
      "name": "HOWL",
      "image": null
    },
    "gold_team_info": {
      "id": 734,
      "name": "GLAMARIS",
      "image": null
    },
    "bracket_info": {
      "id": 242,
      "name": "KQSFL Draft Night 2/27/23",
      "linked_bracket_id": "KQSFL_022723",
      "link_token": "6b8fa6203a8a85887c346ed8ef5f5115",
      "linked_org": null,
      "is_valid": true,
      "is_complete": false,
      "rounds_per_match": 0,
      "wins_per_match": 2,
      "matches_per_opponent": null,
      "report_as_sets": false,
      "add_tiebreaker": false,
      "stage_type": null,
      "auto_warmup": "false",
      "queue_timer": 30,
      "randomize_sides": false,
      "third_place_match": false,
      "stage_tiebreakers": null,
      "tournament": 124
    },
    "linked_match_id": "309613300",
    "match_type": null,
    "match_num": null,
    "blue_score": 2,
    "gold_score": 1,
    "round_num": null,
    "round_name": "Round 1",
    "is_flipped": true,
    "is_complete": true,
    "is_warmup": false,
    "video_link": null,
    "winner_to_team": null,
    "loser_to_team": null,
    "winner_place": null,
    "loser_place": null,
    "bracket": 242,
    "blue_team": 735,
    "gold_team": 734,
    "active_cabinet": null,
    "winner_to_match": null,
    "loser_to_match": null
  },
  {
    "id": 1517,
    "tournament": {
      "id": 124,
      "name": "KQSFL Draft Night 2/27/23",
      "scene": 9,
      "scene_name": "sfl",
      "slug": "kqsfl-draft-night-22723",
      "date": "2023-02-27",
      "is_active": false,
      "location": "",
      "description": "",
      "allow_registration": false,
      "registration_close_date": null,
      "registration_banner": null,
      "accept_payments": false,
      "link_type": "challonge",
      "registration_message": "",
      "payment_message": "",
      "stripe_configured": false,
      "awards": null,
      "require_player_photo": false,
      "assigned_cabinets": [],
      "tidbit_prompt": "Interesting tidbit about yourself",
      "scene_display_name": "South Florida"
    },
    "stage_name": "KQSFL Draft Night 2/27/23",
    "blue_team_info": {
      "id": 730,
      "name": "MASTERJOE",
      "image": null
    },
    "gold_team_info": {
      "id": 733,
      "name": "DAN",
      "image": null
    },
    "bracket_info": {
      "id": 242,
      "name": "KQSFL Draft Night 2/27/23",
      "linked_bracket_id": "KQSFL_022723",
      "link_token": "6b8fa6203a8a85887c346ed8ef5f5115",
      "linked_org": null,
      "is_valid": true,
      "is_complete": false,
      "rounds_per_match": 0,
      "wins_per_match": 2,
      "matches_per_opponent": null,
      "report_as_sets": false,
      "add_tiebreaker": false,
      "stage_type": null,
      "auto_warmup": "false",
      "queue_timer": 30,
      "randomize_sides": false,
      "third_place_match": false,
      "stage_tiebreakers": null,
      "tournament": 124
    },
    "linked_match_id": "309613301",
    "match_type": null,
    "match_num": null,
    "blue_score": 2,
    "gold_score": 0,
    "round_num": null,
    "round_name": "Round 1",
    "is_flipped": true,
    "is_complete": true,
    "is_warmup": false,
    "video_link": null,
    "winner_to_team": null,
    "loser_to_team": null,
    "winner_place": null,
    "loser_place": null,
    "bracket": 242,
    "blue_team": 730,
    "gold_team": 733,
    "active_cabinet": null,
    "winner_to_match": null,
    "loser_to_match": null
  },
  {
    "id": 1518,
    "tournament": {
      "id": 124,
      "name": "KQSFL Draft Night 2/27/23",
      "scene": 9,
      "scene_name": "sfl",
      "slug": "kqsfl-draft-night-22723",
      "date": "2023-02-27",
      "is_active": false,
      "location": "",
      "description": "",
      "allow_registration": false,
      "registration_close_date": null,
      "registration_banner": null,
      "accept_payments": false,
      "link_type": "challonge",
      "registration_message": "",
      "payment_message": "",
      "stripe_configured": false,
      "awards": null,
      "require_player_photo": false,
      "assigned_cabinets": [],
      "tidbit_prompt": "Interesting tidbit about yourself",
      "scene_display_name": "South Florida"
    },
    "stage_name": "KQSFL Draft Night 2/27/23",
    "blue_team_info": {
      "id": 732,
      "name": "PRECIOUS",
      "image": null
    },
    "gold_team_info": {
      "id": 731,
      "name": "KEITH",
      "image": null
    },
    "bracket_info": {
      "id": 242,
      "name": "KQSFL Draft Night 2/27/23",
      "linked_bracket_id": "KQSFL_022723",
      "link_token": "6b8fa6203a8a85887c346ed8ef5f5115",
      "linked_org": null,
      "is_valid": true,
      "is_complete": false,
      "rounds_per_match": 0,
      "wins_per_match": 2,
      "matches_per_opponent": null,
      "report_as_sets": false,
      "add_tiebreaker": false,
      "stage_type": null,
      "auto_warmup": "false",
      "queue_timer": 30,
      "randomize_sides": false,
      "third_place_match": false,
      "stage_tiebreakers": null,
      "tournament": 124
    },
    "linked_match_id": "309613302",
    "match_type": null,
    "match_num": null,
    "blue_score": 2,
    "gold_score": 1,
    "round_num": null,
    "round_name": "Quarterfinals",
    "is_flipped": true,
    "is_complete": true,
    "is_warmup": false,
    "video_link": null,
    "winner_to_team": null,
    "loser_to_team": null,
    "winner_place": null,
    "loser_place": null,
    "bracket": 242,
    "blue_team": 732,
    "gold_team": 731,
    "active_cabinet": null,
    "winner_to_match": null,
    "loser_to_match": null
  },
  {
    "id": 1519,
    "tournament": {
      "id": 124,
      "name": "KQSFL Draft Night 2/27/23",
      "scene": 9,
      "scene_name": "sfl",
      "slug": "kqsfl-draft-night-22723",
      "date": "2023-02-27",
      "is_active": false,
      "location": "",
      "description": "",
      "allow_registration": false,
      "registration_close_date": null,
      "registration_banner": null,
      "accept_payments": false,
      "link_type": "challonge",
      "registration_message": "",
      "payment_message": "",
      "stripe_configured": false,
      "awards": null,
      "require_player_photo": false,
      "assigned_cabinets": [],
      "tidbit_prompt": "Interesting tidbit about yourself",
      "scene_display_name": "South Florida"
    },
    "stage_name": "KQSFL Draft Night 2/27/23",
    "blue_team_info": {
      "id": 730,
      "name": "MASTERJOE",
      "image": null
    },
    "gold_team_info": {
      "id": 735,
      "name": "HOWL",
      "image": null
    },
    "bracket_info": {
      "id": 242,
      "name": "KQSFL Draft Night 2/27/23",
      "linked_bracket_id": "KQSFL_022723",
      "link_token": "6b8fa6203a8a85887c346ed8ef5f5115",
      "linked_org": null,
      "is_valid": true,
      "is_complete": false,
      "rounds_per_match": 0,
      "wins_per_match": 2,
      "matches_per_opponent": null,
      "report_as_sets": false,
      "add_tiebreaker": false,
      "stage_type": null,
      "auto_warmup": "false",
      "queue_timer": 30,
      "randomize_sides": false,
      "third_place_match": false,
      "stage_tiebreakers": null,
      "tournament": 124
    },
    "linked_match_id": "309613303",
    "match_type": null,
    "match_num": null,
    "blue_score": 2,
    "gold_score": 0,
    "round_num": null,
    "round_name": "Quarterfinals",
    "is_flipped": true,
    "is_complete": true,
    "is_warmup": false,
    "video_link": null,
    "winner_to_team": null,
    "loser_to_team": null,
    "winner_place": null,
    "loser_place": null,
    "bracket": 242,
    "blue_team": 730,
    "gold_team": 735,
    "active_cabinet": null,
    "winner_to_match": null,
    "loser_to_match": null
  },
  {
    "id": 1520,
    "tournament": {
      "id": 124,
      "name": "KQSFL Draft Night 2/27/23",
      "scene": 9,
      "scene_name": "sfl",
      "slug": "kqsfl-draft-night-22723",
      "date": "2023-02-27",
      "is_active": false,
      "location": "",
      "description": "",
      "allow_registration": false,
      "registration_close_date": null,
      "registration_banner": null,
      "accept_payments": false,
      "link_type": "challonge",
      "registration_message": "",
      "payment_message": "",
      "stripe_configured": false,
      "awards": null,
      "require_player_photo": false,
      "assigned_cabinets": [],
      "tidbit_prompt": "Interesting tidbit about yourself",
      "scene_display_name": "South Florida"
    },
    "stage_name": "KQSFL Draft Night 2/27/23",
    "blue_team_info": {
      "id": 733,
      "name": "DAN",
      "image": null
    },
    "gold_team_info": {
      "id": 734,
      "name": "GLAMARIS",
      "image": null
    },
    "bracket_info": {
      "id": 242,
      "name": "KQSFL Draft Night 2/27/23",
      "linked_bracket_id": "KQSFL_022723",
      "link_token": "6b8fa6203a8a85887c346ed8ef5f5115",
      "linked_org": null,
      "is_valid": true,
      "is_complete": false,
      "rounds_per_match": 0,
      "wins_per_match": 2,
      "matches_per_opponent": null,
      "report_as_sets": false,
      "add_tiebreaker": false,
      "stage_type": null,
      "auto_warmup": "false",
      "queue_timer": 30,
      "randomize_sides": false,
      "third_place_match": false,
      "stage_tiebreakers": null,
      "tournament": 124
    },
    "linked_match_id": "309613305",
    "match_type": null,
    "match_num": null,
    "blue_score": 2,
    "gold_score": 0,
    "round_num": null,
    "round_name": "Losers Round 1",
    "is_flipped": true,
    "is_complete": true,
    "is_warmup": false,
    "video_link": null,
    "winner_to_team": null,
    "loser_to_team": null,
    "winner_place": null,
    "loser_place": null,
    "bracket": 242,
    "blue_team": 733,
    "gold_team": 734,
    "active_cabinet": null,
    "winner_to_match": null,
    "loser_to_match": null
  },
  {
    "id": 1521,
    "tournament": {
      "id": 124,
      "name": "KQSFL Draft Night 2/27/23",
      "scene": 9,
      "scene_name": "sfl",
      "slug": "kqsfl-draft-night-22723",
      "date": "2023-02-27",
      "is_active": false,
      "location": "",
      "description": "",
      "allow_registration": false,
      "registration_close_date": null,
      "registration_banner": null,
      "accept_payments": false,
      "link_type": "challonge",
      "registration_message": "",
      "payment_message": "",
      "stripe_configured": false,
      "awards": null,
      "require_player_photo": false,
      "assigned_cabinets": [],
      "tidbit_prompt": "Interesting tidbit about yourself",
      "scene_display_name": "South Florida"
    },
    "stage_name": "KQSFL Draft Night 2/27/23",
    "blue_team_info": {
      "id": 733,
      "name": "DAN",
      "image": null
    },
    "gold_team_info": {
      "id": 731,
      "name": "KEITH",
      "image": null
    },
    "bracket_info": {
      "id": 242,
      "name": "KQSFL Draft Night 2/27/23",
      "linked_bracket_id": "KQSFL_022723",
      "link_token": "6b8fa6203a8a85887c346ed8ef5f5115",
      "linked_org": null,
      "is_valid": true,
      "is_complete": false,
      "rounds_per_match": 0,
      "wins_per_match": 2,
      "matches_per_opponent": null,
      "report_as_sets": false,
      "add_tiebreaker": false,
      "stage_type": null,
      "auto_warmup": "false",
      "queue_timer": 30,
      "randomize_sides": false,
      "third_place_match": false,
      "stage_tiebreakers": null,
      "tournament": 124
    },
    "linked_match_id": "309613307",
    "match_type": null,
    "match_num": null,
    "blue_score": 2,
    "gold_score": 0,
    "round_num": null,
    "round_name": "Losers Round 2",
    "is_flipped": true,
    "is_complete": true,
    "is_warmup": false,
    "video_link": null,
    "winner_to_team": null,
    "loser_to_team": null,
    "winner_place": null,
    "loser_place": null,
    "bracket": 242,
    "blue_team": 733,
    "gold_team": 731,
    "active_cabinet": null,
    "winner_to_match": null,
    "loser_to_match": null
  },
  {
    "id": 1522,
    "tournament": {
      "id": 124,
      "name": "KQSFL Draft Night 2/27/23",
      "scene": 9,
      "scene_name": "sfl",
      "slug": "kqsfl-draft-night-22723",
      "date": "2023-02-27",
      "is_active": false,
      "location": "",
      "description": "",
      "allow_registration": false,
      "registration_close_date": null,
      "registration_banner": null,
      "accept_payments": false,
      "link_type": "challonge",
      "registration_message": "",
      "payment_message": "",
      "stripe_configured": false,
      "awards": null,
      "require_player_photo": false,
      "assigned_cabinets": [],
      "tidbit_prompt": "Interesting tidbit about yourself",
      "scene_display_name": "South Florida"
    },
    "stage_name": "KQSFL Draft Night 2/27/23",
    "blue_team_info": {
      "id": 730,
      "name": "MASTERJOE",
      "image": null
    },
    "gold_team_info": {
      "id": 732,
      "name": "PRECIOUS",
      "image": null
    },
    "bracket_info": {
      "id": 242,
      "name": "KQSFL Draft Night 2/27/23",
      "linked_bracket_id": "KQSFL_022723",
      "link_token": "6b8fa6203a8a85887c346ed8ef5f5115",
      "linked_org": null,
      "is_valid": true,
      "is_complete": false,
      "rounds_per_match": 0,
      "wins_per_match": 2,
      "matches_per_opponent": null,
      "report_as_sets": false,
      "add_tiebreaker": false,
      "stage_type": null,
      "auto_warmup": "false",
      "queue_timer": 30,
      "randomize_sides": false,
      "third_place_match": false,
      "stage_tiebreakers": null,
      "tournament": 124
    },
    "linked_match_id": "309613304",
    "match_type": null,
    "match_num": null,
    "blue_score": 2,
    "gold_score": 1,
    "round_num": null,
    "round_name": "Semifinals",
    "is_flipped": true,
    "is_complete": true,
    "is_warmup": false,
    "video_link": null,
    "winner_to_team": null,
    "loser_to_team": null,
    "winner_place": null,
    "loser_place": null,
    "bracket": 242,
    "blue_team": 730,
    "gold_team": 732,
    "active_cabinet": null,
    "winner_to_match": null,
    "loser_to_match": null
  },
  {
    "id": 1523,
    "tournament": {
      "id": 124,
      "name": "KQSFL Draft Night 2/27/23",
      "scene": 9,
      "scene_name": "sfl",
      "slug": "kqsfl-draft-night-22723",
      "date": "2023-02-27",
      "is_active": false,
      "location": "",
      "description": "",
      "allow_registration": false,
      "registration_close_date": null,
      "registration_banner": null,
      "accept_payments": false,
      "link_type": "challonge",
      "registration_message": "",
      "payment_message": "",
      "stripe_configured": false,
      "awards": null,
      "require_player_photo": false,
      "assigned_cabinets": [],
      "tidbit_prompt": "Interesting tidbit about yourself",
      "scene_display_name": "South Florida"
    },
    "stage_name": "KQSFL Draft Night 2/27/23",
    "blue_team_info": {
      "id": 729,
      "name": "SHIPWASH",
      "image": null
    },
    "gold_team_info": {
      "id": 735,
      "name": "HOWL",
      "image": null
    },
    "bracket_info": {
      "id": 242,
      "name": "KQSFL Draft Night 2/27/23",
      "linked_bracket_id": "KQSFL_022723",
      "link_token": "6b8fa6203a8a85887c346ed8ef5f5115",
      "linked_org": null,
      "is_valid": true,
      "is_complete": false,
      "rounds_per_match": 0,
      "wins_per_match": 2,
      "matches_per_opponent": null,
      "report_as_sets": false,
      "add_tiebreaker": false,
      "stage_type": null,
      "auto_warmup": "false",
      "queue_timer": 30,
      "randomize_sides": false,
      "third_place_match": false,
      "stage_tiebreakers": null,
      "tournament": 124
    },
    "linked_match_id": "309613306",
    "match_type": null,
    "match_num": null,
    "blue_score": 2,
    "gold_score": 0,
    "round_num": null,
    "round_name": "Losers Round 2",
    "is_flipped": true,
    "is_complete": true,
    "is_warmup": false,
    "video_link": null,
    "winner_to_team": null,
    "loser_to_team": null,
    "winner_place": null,
    "loser_place": null,
    "bracket": 242,
    "blue_team": 729,
    "gold_team": 735,
    "active_cabinet": null,
    "winner_to_match": null,
    "loser_to_match": null
  },
  {
    "id": 1524,
    "tournament": {
      "id": 124,
      "name": "KQSFL Draft Night 2/27/23",
      "scene": 9,
      "scene_name": "sfl",
      "slug": "kqsfl-draft-night-22723",
      "date": "2023-02-27",
      "is_active": false,
      "location": "",
      "description": "",
      "allow_registration": false,
      "registration_close_date": null,
      "registration_banner": null,
      "accept_payments": false,
      "link_type": "challonge",
      "registration_message": "",
      "payment_message": "",
      "stripe_configured": false,
      "awards": null,
      "require_player_photo": false,
      "assigned_cabinets": [],
      "tidbit_prompt": "Interesting tidbit about yourself",
      "scene_display_name": "South Florida"
    },
    "stage_name": "KQSFL Draft Night 2/27/23",
    "blue_team_info": {
      "id": 733,
      "name": "DAN",
      "image": null
    },
    "gold_team_info": {
      "id": 729,
      "name": "SHIPWASH",
      "image": null
    },
    "bracket_info": {
      "id": 242,
      "name": "KQSFL Draft Night 2/27/23",
      "linked_bracket_id": "KQSFL_022723",
      "link_token": "6b8fa6203a8a85887c346ed8ef5f5115",
      "linked_org": null,
      "is_valid": true,
      "is_complete": false,
      "rounds_per_match": 0,
      "wins_per_match": 2,
      "matches_per_opponent": null,
      "report_as_sets": false,
      "add_tiebreaker": false,
      "stage_type": null,
      "auto_warmup": "false",
      "queue_timer": 30,
      "randomize_sides": false,
      "third_place_match": false,
      "stage_tiebreakers": null,
      "tournament": 124
    },
    "linked_match_id": "309613308",
    "match_type": null,
    "match_num": null,
    "blue_score": 2,
    "gold_score": 1,
    "round_num": null,
    "round_name": "Losers Round 3",
    "is_flipped": true,
    "is_complete": true,
    "is_warmup": false,
    "video_link": null,
    "winner_to_team": null,
    "loser_to_team": null,
    "winner_place": null,
    "loser_place": null,
    "bracket": 242,
    "blue_team": 733,
    "gold_team": 729,
    "active_cabinet": null,
    "winner_to_match": null,
    "loser_to_match": null
  },
  {
    "id": 1525,
    "tournament": {
      "id": 124,
      "name": "KQSFL Draft Night 2/27/23",
      "scene": 9,
      "scene_name": "sfl",
      "slug": "kqsfl-draft-night-22723",
      "date": "2023-02-27",
      "is_active": false,
      "location": "",
      "description": "",
      "allow_registration": false,
      "registration_close_date": null,
      "registration_banner": null,
      "accept_payments": false,
      "link_type": "challonge",
      "registration_message": "",
      "payment_message": "",
      "stripe_configured": false,
      "awards": null,
      "require_player_photo": false,
      "assigned_cabinets": [],
      "tidbit_prompt": "Interesting tidbit about yourself",
      "scene_display_name": "South Florida"
    },
    "stage_name": "KQSFL Draft Night 2/27/23",
    "blue_team_info": {
      "id": 733,
      "name": "DAN",
      "image": null
    },
    "gold_team_info": {
      "id": 732,
      "name": "PRECIOUS",
      "image": null
    },
    "bracket_info": {
      "id": 242,
      "name": "KQSFL Draft Night 2/27/23",
      "linked_bracket_id": "KQSFL_022723",
      "link_token": "6b8fa6203a8a85887c346ed8ef5f5115",
      "linked_org": null,
      "is_valid": true,
      "is_complete": false,
      "rounds_per_match": 0,
      "wins_per_match": 2,
      "matches_per_opponent": null,
      "report_as_sets": false,
      "add_tiebreaker": false,
      "stage_type": null,
      "auto_warmup": "false",
      "queue_timer": 30,
      "randomize_sides": false,
      "third_place_match": false,
      "stage_tiebreakers": null,
      "tournament": 124
    },
    "linked_match_id": "309613309",
    "match_type": null,
    "match_num": null,
    "blue_score": 0,
    "gold_score": 2,
    "round_num": null,
    "round_name": "Losers Round 4",
    "is_flipped": true,
    "is_complete": true,
    "is_warmup": false,
    "video_link": null,
    "winner_to_team": null,
    "loser_to_team": null,
    "winner_place": null,
    "loser_place": null,
    "bracket": 242,
    "blue_team": 733,
    "gold_team": 732,
    "active_cabinet": null,
    "winner_to_match": null,
    "loser_to_match": null
  },
  {
    "id": 1526,
    "tournament": {
      "id": 124,
      "name": "KQSFL Draft Night 2/27/23",
      "scene": 9,
      "scene_name": "sfl",
      "slug": "kqsfl-draft-night-22723",
      "date": "2023-02-27",
      "is_active": false,
      "location": "",
      "description": "",
      "allow_registration": false,
      "registration_close_date": null,
      "registration_banner": null,
      "accept_payments": false,
      "link_type": "challonge",
      "registration_message": "",
      "payment_message": "",
      "stripe_configured": false,
      "awards": null,
      "require_player_photo": false,
      "assigned_cabinets": [],
      "tidbit_prompt": "Interesting tidbit about yourself",
      "scene_display_name": "South Florida"
    },
    "stage_name": "KQSFL Draft Night 2/27/23",
    "blue_team_info": {
      "id": 732,
      "name": "PRECIOUS",
      "image": null
    },
    "gold_team_info": {
      "id": 730,
      "name": "MASTERJOE",
      "image": null
    },
    "bracket_info": {
      "id": 242,
      "name": "KQSFL Draft Night 2/27/23",
      "linked_bracket_id": "KQSFL_022723",
      "link_token": "6b8fa6203a8a85887c346ed8ef5f5115",
      "linked_org": null,
      "is_valid": true,
      "is_complete": false,
      "rounds_per_match": 0,
      "wins_per_match": 2,
      "matches_per_opponent": null,
      "report_as_sets": false,
      "add_tiebreaker": false,
      "stage_type": null,
      "auto_warmup": "false",
      "queue_timer": 30,
      "randomize_sides": false,
      "third_place_match": false,
      "stage_tiebreakers": null,
      "tournament": 124
    },
    "linked_match_id": "309613310",
    "match_type": null,
    "match_num": null,
    "blue_score": 1,
    "gold_score": 2,
    "round_num": null,
    "round_name": "Finals",
    "is_flipped": true,
    "is_complete": true,
    "is_warmup": false,
    "video_link": null,
    "winner_to_team": null,
    "loser_to_team": null,
    "winner_place": null,
    "loser_place": null,
    "bracket": 242,
    "blue_team": 732,
    "gold_team": 730,
    "active_cabinet": null,
    "winner_to_match": null,
    "loser_to_match": null
  }
]